pytomlenv/__init__.py
pytomlenv/main.py
pytomlenv-0.2.0.dist-info/LICENSE
pytomlenv-0.2.0.dist-info/METADATA
pytomlenv-0.2.0.dist-info/WHEEL
pytomlenv-0.2.0.dist-info/RECORD
